cir4mics/.idea/.gitignore
cir4mics/.idea/cir4mics.iml
cir4mics/.idea/inspectionProfiles/profiles_settings.xml
cir4mics/.idea/misc.xml
cir4mics/.idea/modules.xml
cir4mics/.idea/other.xml
cir4mics/.idea/vcs.xml
cir4mics/.ipynb_checkpoints/Analyse_deformed-checkpoint.py
cir4mics/.ipynb_checkpoints/Dynamics-checkpoint.ipynb
cir4mics/.ipynb_checkpoints/Include_models-checkpoint.ipynb
cir4mics/.ipynb_checkpoints/NPC_testlab-checkpoint.ipynb
cir4mics/.ipynb_checkpoints/call_functions-checkpoint.py
cir4mics/.ipynb_checkpoints/npc-checkpoint.py
cir4mics/Analyse_deformed.py
cir4mics/DeformNPC.py
cir4mics/NPC_plotting.py
cir4mics/Nups_Info.py
cir4mics/__init__.py
cir4mics/call_functions.py
cir4mics/exportCSV.py
cir4mics/npc.py
cir4mics/utility.py
cir4mics-0.2.10.dist-info/LICENSE
cir4mics-0.2.10.dist-info/METADATA
cir4mics-0.2.10.dist-info/WHEEL
cir4mics-0.2.10.dist-info/RECORD
